{
  "resourceType": "ValueSet",
  "id": "us-quality-core-positive-medication-admin-status",
  "url": "http://hl7.org/fhir/us/quality-core/ValueSet/us-quality-core-positive-medication-admin-status",
  "version": "1.0.0",
  "name": "PositiveMedicationAdministrationStatus",
  "title": "Positive MedicationAdministration Status",
  "status": "active",
  "experimental": false,
  "date": "2026-06-30",
  "publisher": "HL7 International / Clinical Quality Information",
  "contact": [
    {
      "name": "Clinical Quality Information WG",
      "telecom": [
        {
          "system": "url",
          "value": "http://www.hl7.org/Special/committees/cqi"
        }
      ]
    }
  ],
  "description": "This value set defines the set of codes that indicate a positive medication administration status (i.e. codes that indicate at least some medication is being or was administered)",
  "jurisdiction": [
    {
      "coding": [
        {
          "system": "urn:iso:std:iso:3166",
          "code": "US",
          "display": "United States of America"
        }
      ]
    }
  ],
  "purpose": "This value set was defined to support the set of medication administration statuses in FHIR that indicate a positive status (i.e. all the codes from the http://terminology.hl7.org/CodeSystem/medication-admin-status code system that indicate at least some medication is being or was administered).",
  "compose": {
    "include": [
      {
        "system": "http://terminology.hl7.org/CodeSystem/medication-admin-status",
        "concept": [
          {
            "code": "in-progress",
            "display": "In Progress"
          },
          {
            "code": "on-hold",
            "display": "On Hold"
          },
          {
            "code": "completed",
            "display": "Completed"
          },
          {
            "code": "stopped",
            "display": "Stopped"
          }
        ]
      }
    ]
  }
}
